pypomodoro/__init__.py
pypomodoro/gui.py
pypomodoro/main.py
pypomodoro/pomodoro.py
test/__init__.py
test/test_gui.py
test/test_pomodoro.py
pypomodoro-0.7.1.dist-info/METADATA
pypomodoro-0.7.1.dist-info/WHEEL
pypomodoro-0.7.1.dist-info/entry_points.txt
pypomodoro-0.7.1.dist-info/top_level.txt
pypomodoro-0.7.1.dist-info/RECORD
