Metadata-Version: 2.1
Name: pypomodoro
Version: 0.7.1
Summary: Displays a full screen pomodoro timer in the terminal
Home-page: https://github.com/lostways/pypomodoro
Author: Andrew Lowe
Author-email: andrew@lostways.com
License: MIT
Classifier: License :: OSI Approved :: MIT License
Classifier: Programming Language :: Python :: 3
Classifier: Programming Language :: Python :: 3.7
